<?xml version="1.0"?>
<annotation>
    <filename>000000000.jpg</filename>
    <source>
        <annotation>ArcGIS Pro 2.1</annotation>
    </source>
    <size>
        <width>224</width>
        <height>224</height>
        <depth>3</depth>
    </size>
    <object>
        <name>1</name>
        <bndbox>
            <xmin>58.47</xmin>
            <ymin>152.31</ymin>
            <xmax>69.58</xmax>
            <ymax>163.43</ymax>
        </bndbox>
    </object>
    <object>
        <name>1</name>
        <bndbox>
            <xmin>10.32</xmin>
            <ymin>205.68</ymin>
            <xmax>21.43</xmax>
            <ymax>216.80</ymax>
        </bndbox>
    </object>
    <object>
        <name>1</name>
        <bndbox>
            <xmin>40.37</xmin>
            <ymin>0.00</ymin>
            <xmax>50.97</xmax>
            <ymax>3.89</ymax>
        </bndbox>
    </object>
    <object>
        <name>1</name>
        <bndbox>
            <xmin>46.67</xmin>
            <ymin>41.29</ymin>
            <xmax>57.79</xmax>
            <ymax>52.40</ymax>
        </bndbox>
    </object>
</annotation>
